rolexboost/__init__.py
rolexboost/algorithms.py
rolexboost/exceptions.py
rolexboost/lib.py
rolexboost/util.py
rolexboost-0.0.1.dist-info/LICENSE
rolexboost-0.0.1.dist-info/METADATA
rolexboost-0.0.1.dist-info/WHEEL
rolexboost-0.0.1.dist-info/top_level.txt
rolexboost-0.0.1.dist-info/RECORD
