Metadata-Version: 2.1
Name: rolexboost
Version: 0.0.1
Summary: Unofficial implementation of RolexBoost: A Rotation-Based Boosting Algorithm With Adaptive Loss Functions
Home-page: https://github.com/Vopaaz/RolexBoost
Author: Vopaaz, MichaelYangg
Author-email: liyifan945@163.com
License: UNKNOWN
Platform: UNKNOWN
Classifier: Programming Language :: Python :: 3.6
Classifier: Programming Language :: Python :: 3.7
Classifier: License :: OSI Approved :: MIT License
Requires-Dist: scikit-learn (>=0.22.0)
Requires-Dist: numpy (>=1.18.0)
Requires-Dist: scipy (>=1.4.0)
